{
  "General information": {
    "Developer": {"value": "Meta Platforms", "color": "grey"},
    "Year of publication": {"value": 2009, "color": "grey"},
    "Number of downloads (Play Store)": {"value": "5 billion", "color": "grey"},
    "Costs": {"value": "—", "color": "grey"}
  },
  "Environment": {
    "Android": {"value": "yes", "color": "green"},
    "iOS": {"value": "yes", "color": "green"},
    "Desktop": {"value": "Windows, macOS", "color": "yellow"},
    "Web browser": {"value": "yes", "color": "green"}
  },
  "Usability": {
    "Multiple accounts/profiles (multi-account)": {"value": "yes", "color": "green"},
    "Use on multiple devices (in addition to mobile device)": {"value": "up to four additional devices", "color": "yellow"},
    "Find/add contacts": {"value": "Phone number", "color": "grey"}
  },
  "Security": {
    "Open Source": {"value": "no", "color": "red"},
    "Comes without proprietary libraries": {"value": "no", "color": "red"},
    "Encryption protocol / library": {"value": "Signal Protocol (unverifable)", "color": "orange"},
    "End-to-end encryption": {"value": "yes", "color": "green"},
    "Post-quantum encryption": {"value": "no", "color": "red"},
    "Contact verification possible": {"value": "yes", "color": "green"},
    "Notification if contact's fingerprint changes": {"value": "must be enabled", "color": "yellow"},
    "Last security review/audit": {"value": 2024, "color": "grey"}
  },
  "Privacy": {
    "Tracker integration": {"value": "no", "color": "green"},
    "Use without phone number possible": {"value": "no, forwarding to Facebook", "color": "red"},
    "Avoids / Protects metadata during use": {"value": "no", "color": "red"},
    "Reasonably useful without sharing the contact list": {"value": "no", "color": "red"},
    "Supported push notification services": {"value": "Google (FCM), Apple (APN), Direct connection (Android)", "color": "green"},
    "Advertising-free": {"value": "no", "color": "red"}
  },
  "Sustainability": {
    "Centralized / Federated / Decentralized": {"value": "centralized", "color": "red"},
    "Infrastructure hosting": {"value": "Meta, Amazon", "color": "red"},
    "Transparency / Financing (Including donations)": {"value": "non-transparent", "color": "red"},
    "Availability": {"value": "Website, Play Store, App Store", "color": "yellow"},
    "Legal jurisdiction": {"value": "USA", "color": "red"}
  },
  "Functions": {
    "Voice messages": {"value": "yes", "color": "green"},
    "Audio-/Video-chats": {"value": "yes", "color": "green"},
    "Group chats": {"value": "yes", "color": "green"},
    "Maximum number of participants group chat": {"value": 1024, "color": "green"},
    "File exchange": {"value": "yes", "color": "green"},
    "Self-destructing messages": {"value": "yes", "color": "grey"}
  },
  "Backup": {
    "Storage location": {"value": "locally and Cloud (iCloud/Google Drive)", "color": "green"},
    "Automated": {"value": "after setup", "color": "green"},
    "Encrypted": {"value": "for iOS keys with the provider (unless ADP is active)", "color": "yellow"}
  },
  "Kuketz-Blog": {
    "Link to review": {"value": "—", "color": "grey"},
    "Operability / Target group": {"value": "Beginner", "color": "grey"},
    "(subjective) Recommendation": {"value": "no", "color": "red"}
  }
}
